fbpcs/__init__.py
fbpcs/decorator/__init__.py
fbpcs/decorator/error_handler.py
fbpcs/entity/__init__.py
fbpcs/entity/cluster_instance.py
fbpcs/entity/container_instance.py
fbpcs/entity/file_information.py
fbpcs/entity/instance_base.py
fbpcs/entity/log_event.py
fbpcs/entity/mpc_game_config.py
fbpcs/entity/mpc_instance.py
fbpcs/entity/subnet.py
fbpcs/entity/vpc_instance.py
fbpcs/error/__init__.py
fbpcs/error/owdl.py
fbpcs/error/pcs.py
fbpcs/error/mapper/__init__.py
fbpcs/error/mapper/aws.py
fbpcs/gateway/__init__.py
fbpcs/gateway/cloudwatch.py
fbpcs/gateway/ec2.py
fbpcs/gateway/ecs.py
fbpcs/gateway/s3.py
fbpcs/mapper/__init__.py
fbpcs/mapper/aws.py
fbpcs/metrics/__init__.py
fbpcs/metrics/emitter.py
fbpcs/repository/__init__.py
fbpcs/repository/instance_local.py
fbpcs/repository/instance_s3.py
fbpcs/repository/mpc_game_repository.py
fbpcs/repository/mpc_instance.py
fbpcs/repository/mpc_instance_local.py
fbpcs/repository/mpc_instance_s3.py
fbpcs/service/__init__.py
fbpcs/service/container.py
fbpcs/service/container_aws.py
fbpcs/service/log.py
fbpcs/service/log_cloudwatch.py
fbpcs/service/mpc.py
fbpcs/service/mpc_game.py
fbpcs/service/onedocker.py
fbpcs/service/storage.py
fbpcs/service/storage_s3.py
fbpcs/util/__init__.py
fbpcs/util/arg_builder.py
fbpcs/util/reflect.py
fbpcs/util/s3path.py
fbpcs/util/typing.py
fbpcs/util/yaml.py
onedocker/__init__.py
onedocker/common/__init__.py
onedocker/common/env.py
onedocker/common/util.py
onedocker/script/__init__.py
onedocker/script/runner/__init__.py
onedocker/script/runner/__main__.py
onedocker/script/runner/onedocker_runner.py
onedocker/tests/__init__.py
fbpcs-0.4.0.dist-info/LICENSE
fbpcs-0.4.0.dist-info/METADATA
fbpcs-0.4.0.dist-info/WHEEL
fbpcs-0.4.0.dist-info/top_level.txt
fbpcs-0.4.0.dist-info/RECORD
